{
  "$schema": "https://raw.githubusercontent.com/dotnet/docfx/main/schemas/docfx.schema.json",
  "build": {
    "content": [
      {
        "files": [
          "**/*.{md,yml}"
        ],
        "exclude": [
          "_site/**"
        ]
      }
    ],
    "resource": [
      {
        "files": [
          "images/**",
          "assets/**"
        ]
      }
    ],
    "output": "_site",
    "template": [
      "default",
      "modern",
      "bonsai/template",
      "template"
    ],
    "globalMetadata": {
      "_appName": "ucl-open",
      "_appTitle": "ucl-open",
      "_enableSearch": true,
      "pdf": false
    },
    "markdownEngineProperties": {
      "markdigExtensions": [
        "attributes",
        "customcontainers"
      ]
    }
  }
}